{"cacheUntil":1521943328881,"data":{"query":"{\"query\": \"query{rateLimit(dryRun: false){cost, remaining, resetAt}\\nnode(id: \\\"MDExOlB1bGxSZXF1ZXN0MzA3MDQzNDI=\\\"){... on PullRequest{comments(first: 100,after: \\\"Y3Vyc29yOnYyOpHOBKIWVg==\\\"){pageInfo{endCursor\\nhasNextPage}\\nnodes{author{... on User{login\\nname\\nemail\\navatarUrl\\nurl\\nid\\n__typename}\\n... on Bot{login\\nid\\n__typename}}\\ncreatedAt\\nid\\n__typename}}\\nid\\n__typename}}}\"}","body":"{\"data\":{\"rateLimit\":{\"cost\":1,\"remaining\":4658,\"resetAt\":\"2018-03-24T02:07:42Z\"},\"node\":{\"comments\":{\"pageInfo\":{\"endCursor\":\"Y3Vyc29yOnYyOpHOBKKN+w==\",\"hasNextPage\":false},\"nodes\":[{\"author\":{\"login\":\"c0b41\",\"name\":\"Ayhan\",\"email\":\"ayhankuru@yandex.com.tr\",\"avatarUrl\":\"https://avatars1.githubusercontent.com/u/2834954?v=4\",\"url\":\"https://github.com/c0b41\",\"id\":\"MDQ6VXNlcjI4MzQ5NTQ=\",\"__typename\":\"User\"},\"createdAt\":\"2015-03-08T10:18:47Z\",\"id\":\"MDEyOklzc3VlQ29tbWVudDc3NzQyMTU5\",\"__typename\":\"IssueComment\"},{\"author\":{\"login\":\"c0b41\",\"name\":\"Ayhan\",\"email\":\"ayhankuru@yandex.com.tr\",\"avatarUrl\":\"https://avatars1.githubusercontent.com/u/2834954?v=4\",\"url\":\"https://github.com/c0b41\",\"id\":\"MDQ6VXNlcjI4MzQ5NTQ=\",\"__typename\":\"User\"},\"createdAt\":\"2015-03-08T13:03:46Z\",\"id\":\"MDEyOklzc3VlQ29tbWVudDc3NzQ3NzE0\",\"__typename\":\"IssueComment\"},{\"author\":{\"login\":\"c0b41\",\"name\":\"Ayhan\",\"email\":\"ayhankuru@yandex.com.tr\",\"avatarUrl\":\"https://avatars1.githubusercontent.com/u/2834954?v=4\",\"url\":\"https://github.com/c0b41\",\"id\":\"MDQ6VXNlcjI4MzQ5NTQ=\",\"__typename\":\"User\"},\"createdAt\":\"2015-03-08T13:32:51Z\",\"id\":\"MDEyOklzc3VlQ29tbWVudDc3NzQ5MDQ1\",\"__typename\":\"IssueComment\"},{\"author\":{\"login\":\"KiPSOFT\",\"name\":\"Serkan KOCAMAN\",\"email\":\"newkipsoftware@gmail.com\",\"avatarUrl\":\"https://avatars0.githubusercontent.com/u/2437923?v=4\",\"url\":\"https://github.com/KiPSOFT\",\"id\":\"MDQ6VXNlcjI0Mzc5MjM=\",\"__typename\":\"User\"},\"createdAt\":\"2015-03-08T17:13:21Z\",\"id\":\"MDEyOklzc3VlQ29tbWVudDc3NzYyMDQz\",\"__typename\":\"IssueComment\"}]},\"id\":\"MDExOlB1bGxSZXF1ZXN0MzA3MDQzNDI=\",\"__typename\":\"PullRequest\"}}}","status":200,"headers":{"server":"GitHub.com","date":"Sat, 24 Mar 2018 02:02:08 GMT","content-type":"application/json; charset=utf-8","content-length":"1584","connection":"close","status":"200 OK","x-ratelimit-limit":"5000","x-ratelimit-remaining":"4658","x-ratelimit-reset":"1521857262","cache-control":"no-cache","x-oauth-scopes":"read:org, repo, user","x-accepted-oauth-scopes":"repo","x-github-media-type":"github.v4; format=json","access-control-expose-headers":"ETag, Link, Retry-After, X-GitHub-OTP, X-RateLimit-Limit, X-RateLimit-Remaining, X-RateLimit-Reset, X-OAuth-Scopes, X-Accepted-OAuth-Scopes, X-Poll-Interval","access-control-allow-origin":"*","strict-transport-security":"max-age=31536000; includeSubdomains; preload","x-frame-options":"deny","x-content-type-options":"nosniff","x-xss-protection":"1; mode=block","referrer-policy":"origin-when-cross-origin, strict-origin-when-cross-origin","content-security-policy":"default-src 'none'","x-runtime-rack":"0.076756","x-github-request-id":"C9B4:E9B9:1760440:33FE68E:5AB5B1A0"}}}