{"cacheUntil":1521958108998,"data":{"query":"{\"query\": \"query{rateLimit(dryRun: false){cost, remaining, resetAt}\\nnode(id: \\\"MDU6SXNzdWU1Njk0Mzc1MQ==\\\"){... on Issue{comments(first: 100,after: \\\"Y3Vyc29yOnYyOpHOBGAFwg==\\\"){pageInfo{endCursor\\nhasNextPage}\\nnodes{author{... on User{login\\nname\\nemail\\navatarUrl\\nurl\\nid\\n__typename}\\n... on Bot{login\\nid\\n__typename}}\\ncreatedAt\\nid\\n__typename}}\\nid\\n__typename}}}\"}","body":"{\"data\":{\"rateLimit\":{\"cost\":1,\"remaining\":4759,\"resetAt\":\"2018-03-24T06:43:50Z\"},\"node\":{\"comments\":{\"pageInfo\":{\"endCursor\":\"Y3Vyc29yOnYyOpHOBGA/Ow==\",\"hasNextPage\":false},\"nodes\":[{\"author\":{\"login\":\"XadillaX\",\"name\":\"Khaidi Chu\",\"email\":\"i@2333.moe\",\"avatarUrl\":\"https://avatars3.githubusercontent.com/u/2842176?v=4\",\"url\":\"https://github.com/XadillaX\",\"id\":\"MDQ6VXNlcjI4NDIxNzY=\",\"__typename\":\"User\"},\"createdAt\":\"2015-02-08T08:25:32Z\",\"id\":\"MDEyOklzc3VlQ29tbWVudDczNDAxODQz\",\"__typename\":\"IssueComment\"},{\"author\":{\"login\":\"iissnan\",\"name\":\"Vi\",\"email\":\"\",\"avatarUrl\":\"https://avatars3.githubusercontent.com/u/32269?v=4\",\"url\":\"https://github.com/iissnan\",\"id\":\"MDQ6VXNlcjMyMjY5\",\"__typename\":\"User\"},\"createdAt\":\"2015-02-08T08:28:02Z\",\"id\":\"MDEyOklzc3VlQ29tbWVudDczNDAxOTA3\",\"__typename\":\"IssueComment\"},{\"author\":{\"login\":\"XadillaX\",\"name\":\"Khaidi Chu\",\"email\":\"i@2333.moe\",\"avatarUrl\":\"https://avatars3.githubusercontent.com/u/2842176?v=4\",\"url\":\"https://github.com/XadillaX\",\"id\":\"MDQ6VXNlcjI4NDIxNzY=\",\"__typename\":\"User\"},\"createdAt\":\"2015-02-08T08:29:00Z\",\"id\":\"MDEyOklzc3VlQ29tbWVudDczNDAxOTMz\",\"__typename\":\"IssueComment\"},{\"author\":{\"login\":\"fengmk2\",\"name\":\"fengmk2\",\"email\":\"fengmk2@gmail.com\",\"avatarUrl\":\"https://avatars0.githubusercontent.com/u/156269?v=4\",\"url\":\"https://github.com/fengmk2\",\"id\":\"MDQ6VXNlcjE1NjI2OQ==\",\"__typename\":\"User\"},\"createdAt\":\"2015-02-08T09:10:05Z\",\"id\":\"MDEyOklzc3VlQ29tbWVudDczNDAyOTg0\",\"__typename\":\"IssueComment\"},{\"author\":{\"login\":\"fengmk2\",\"name\":\"fengmk2\",\"email\":\"fengmk2@gmail.com\",\"avatarUrl\":\"https://avatars0.githubusercontent.com/u/156269?v=4\",\"url\":\"https://github.com/fengmk2\",\"id\":\"MDQ6VXNlcjE1NjI2OQ==\",\"__typename\":\"User\"},\"createdAt\":\"2015-02-08T09:40:20Z\",\"id\":\"MDEyOklzc3VlQ29tbWVudDczNDAzNzY3\",\"__typename\":\"IssueComment\"},{\"author\":{\"login\":\"fengmk2\",\"name\":\"fengmk2\",\"email\":\"fengmk2@gmail.com\",\"avatarUrl\":\"https://avatars0.githubusercontent.com/u/156269?v=4\",\"url\":\"https://github.com/fengmk2\",\"id\":\"MDQ6VXNlcjE1NjI2OQ==\",\"__typename\":\"User\"},\"createdAt\":\"2015-02-08T13:31:43Z\",\"id\":\"MDEyOklzc3VlQ29tbWVudDczNDEwODc2\",\"__typename\":\"IssueComment\"},{\"author\":{\"login\":\"iissnan\",\"name\":\"Vi\",\"email\":\"\",\"avatarUrl\":\"https://avatars3.githubusercontent.com/u/32269?v=4\",\"url\":\"https://github.com/iissnan\",\"id\":\"MDQ6VXNlcjMyMjY5\",\"__typename\":\"User\"},\"createdAt\":\"2015-02-08T13:50:11Z\",\"id\":\"MDEyOklzc3VlQ29tbWVudDczNDExNTM0\",\"__typename\":\"IssueComment\"},{\"author\":{\"login\":\"popomore\",\"name\":\"Haoliang Gao\",\"email\":\"sakura9515@gmail.com\",\"avatarUrl\":\"https://avatars1.githubusercontent.com/u/360661?v=4\",\"url\":\"https://github.com/popomore\",\"id\":\"MDQ6VXNlcjM2MDY2MQ==\",\"__typename\":\"User\"},\"createdAt\":\"2015-02-08T15:50:30Z\",\"id\":\"MDEyOklzc3VlQ29tbWVudDczNDE2NTA3\",\"__typename\":\"IssueComment\"}]},\"id\":\"MDU6SXNzdWU1Njk0Mzc1MQ==\",\"__typename\":\"Issue\"}}}","status":200,"headers":{"date":"Sat, 24 Mar 2018 06:08:31 GMT","content-type":"application/json; charset=utf-8","content-length":"2818","connection":"close","server":"GitHub.com","status":"200 OK","x-ratelimit-limit":"5000","x-ratelimit-remaining":"4759","x-ratelimit-reset":"1521873830","cache-control":"no-cache","x-oauth-scopes":"repo, user","x-accepted-oauth-scopes":"repo","x-github-media-type":"github.v4; format=json","access-control-expose-headers":"ETag, Link, Retry-After, X-GitHub-OTP, X-RateLimit-Limit, X-RateLimit-Remaining, X-RateLimit-Reset, X-OAuth-Scopes, X-Accepted-OAuth-Scopes, X-Poll-Interval","access-control-allow-origin":"*","strict-transport-security":"max-age=31536000; includeSubdomains; preload","x-frame-options":"deny","x-content-type-options":"nosniff","x-xss-protection":"1; mode=block","referrer-policy":"origin-when-cross-origin, strict-origin-when-cross-origin","content-security-policy":"default-src 'none'","x-runtime-rack":"0.087638","vary":"Accept-Encoding","x-github-request-id":"3920:142D:BD6CE:FE4C6:5AB5EB5E"}}}